Workbook

Sheet Assumptions
A1: parameter_key | B1: value | C1: unit | D1: notes
A2: tenant_count | B2: 100 | C2: count | D2: Paying customers (example)
A3: days_per_month | B3: 30 | C3: days
A4: jobs_per_tenant_per_day | B4: 50 | C4: count | D4: Agent/copilot jobs per tenant per day
A5: tokens_in_per_job | B5: 4000 | C5: tokens
A6: tokens_out_per_job | B6: 800 | C6: tokens
A7: llm_price_in_per_million_tokens | B7: 0.50 | C7: USD_per_1M_tokens | D7: Your blended cost if you pay the provider
A8: llm_price_out_per_million_tokens | B8: 1.50 | C8: USD_per_1M_tokens
A9: storage_gb_per_tenant_month | B9: 25 | C9: GB_month | D9: Audit logs artifacts embeddings (illustrative)
A10: storage_usd_per_gb_month | B10: 0.023 | C10: USD_per_GB_month | D10: Object storage class blended
A11: egress_gb_per_tenant_month | B11: 5 | C11: GB_month | D11: Exports portal downloads
A12: egress_usd_per_gb | B12: 0.09 | C12: USD_per_GB | D12: Internet egress illustrative
A13: shared_vcpu_for_app_pool | B13: 16 | C13: vCPU | D13: Shared multitenant app and workers (illustrative)
A14: vcpu_hour_usd | B14: 0.04 | C14: USD_per_vcpu_hour | D14: Simplify: flat rate times vCPU-hours
A15: managed_db_usd_month | B15: 200 | C15: USD_month | D15: Postgres or equivalent managed primary
A16: fixed_saas_overhead_usd_month | B16: 500 | C16: USD_month | D16: Auth, email, CI, observability, misc vendors
A17: revenue_per_tenant_month | B17: 98 | C17: USD_month | D17: Illustrative: e.g. 2 seats at 49
A18: stripe_fee_percent | B18: 0.029 | C18: ratio | D18: Card processing percent
A19: stripe_fixed_usd_per_charge | B19: 0.30 | C19: USD_per_successful_charge
A20: headcount_fte_sales | B20: 0 | C20: count | D20: FTE equivalents
A21: headcount_fte_engineering | B21: 1 | C21: count
A22: headcount_fte_support | B22: 0.25 | C22: count
A23: fully_loaded_cost_usd_per_fte_month | B23: 18000 | C23: USD_month_per_FTE | D23: Salary+benefits+payroll tax+tools; adjust hard
A24: legal_retainer_usd_month | B24: 0 | C24: USD_month | D24: Outside counsel placeholder
A25: accounting_bookkeeping_usd_month | B25: 500 | C25: USD_month
A26: insurance_usd_month | B26: 200 | C26: USD_month | D26: GL+E&O placeholder
A27: runway_months_cash | B27: 6 | C27: months | D27: Cash you can burn without new revenue
A28: founder_draw_usd_month | B28: 8000 | C28: USD_month | D28: Personal burn covered from business or savings
A29: customer_acquisition_cost_usd | B29: 500 | C29: USD_per_customer | D29: Blended CAC placeholder
A30: annual_churn_percent | B30: 15 | C30: percent_per_year | D30: Logo churn illustrative
A31: support_tickets_per_tenant_month | B31: 2 | C31: count | D31: For staffing model
A32: minutes_per_ticket | B32: 25 | C32: minutes | D32: Handle time illustrative

Sheet Monthly_P_L
A1: section | B1: line_item | C1: amount_usd | D1: driver_or_formula_notes
A2: Revenue | B2: Subscription MRR | C2: =INDEX(Assumptions!$B:$B,MATCH("tenant_count",Assumptions!$A:$A,0))*INDEX(Assumptions!$B:$B,MATCH("revenue_per_tenant_month",Assumptions!$A:$A,0)) | D2: tenant_count * revenue_per_tenant_month
A3: Revenue | B3: Professional services (one-time) | C3: 0 | D3: Edit if booked
A4: Revenue | B4: Other | C4: 0 | D4: Optional
A6: COGS | B6: LLM API (if you absorb) | C6: =INDEX(Assumptions!$B:$B,MATCH("tenant_count",Assumptions!$A:$A,0))*INDEX(Assumptions!$B:$B,MATCH("jobs_per_tenant_per_day",Assumptions!$A:$A,0))*INDEX(Assumptions!$B:$B,MATCH("days_per_month",Assumptions!$A:$A,0))*((INDEX(Assumptions!$B:$B,MATCH("tokens_in_per_job",Assumptions!$A:$A,0))/1000000)*INDEX(Assumptions!$B:$B,MATCH("llm_price_in_per_million_tokens",Assumptions!$A:$A,0))+(INDEX(Assumptions!$B:$B,MATCH("tokens_out_per_job",Assumptions!$A:$A,0))/1000000)*INDEX(Assumptions!$B:$B,MATCH("llm_price_out_per_million_tokens",Assumptions!$A:$A,0))) | D6: Fleet token cost
A7: COGS | B7: Object storage | C7: =INDEX(Assumptions!$B:$B,MATCH("tenant_count",Assumptions!$A:$A,0))*INDEX(Assumptions!$B:$B,MATCH("storage_gb_per_tenant_month",Assumptions!$A:$A,0))*INDEX(Assumptions!$B:$B,MATCH("storage_usd_per_gb_month",Assumptions!$A:$A,0))
A8: COGS | B8: Egress | C8: =INDEX(Assumptions!$B:$B,MATCH("tenant_count",Assumptions!$A:$A,0))*INDEX(Assumptions!$B:$B,MATCH("egress_gb_per_tenant_month",Assumptions!$A:$A,0))*INDEX(Assumptions!$B:$B,MATCH("egress_usd_per_gb",Assumptions!$A:$A,0))
A9: COGS | B9: Compute (shared pool) | C9: =INDEX(Assumptions!$B:$B,MATCH("shared_vcpu_for_app_pool",Assumptions!$A:$A,0))*24*INDEX(Assumptions!$B:$B,MATCH("days_per_month",Assumptions!$A:$A,0))*INDEX(Assumptions!$B:$B,MATCH("vcpu_hour_usd",Assumptions!$A:$A,0))
A10: COGS | B10: Managed database | C10: =INDEX(Assumptions!$B:$B,MATCH("managed_db_usd_month",Assumptions!$A:$A,0))
A11: COGS | B11: Fixed vendor overhead (COGS allocation) | C11: =INDEX(Assumptions!$B:$B,MATCH("fixed_saas_overhead_usd_month",Assumptions!$A:$A,0))
A12: COGS | B12: Payment processing fees | C12: =INDEX(Assumptions!$B:$B,MATCH("tenant_count",Assumptions!$A:$A,0))*(INDEX(Assumptions!$B:$B,MATCH("stripe_fee_percent",Assumptions!$A:$A,0))*INDEX(Assumptions!$B:$B,MATCH("revenue_per_tenant_month",Assumptions!$A:$A,0))+INDEX(Assumptions!$B:$B,MATCH("stripe_fixed_usd_per_charge",Assumptions!$A:$A,0)))
A14: Gross profit | B14: Gross profit (after COGS incl. payment fees) | C14: =SUM(C2:C4)-SUM(C6:C12)
A16: OpEx | B16: Payroll (fully loaded) | C16: =(INDEX(Assumptions!$B:$B,MATCH("headcount_fte_sales",Assumptions!$A:$A,0))+INDEX(Assumptions!$B:$B,MATCH("headcount_fte_engineering",Assumptions!$A:$A,0))+INDEX(Assumptions!$B:$B,MATCH("headcount_fte_support",Assumptions!$A:$A,0)))*INDEX(Assumptions!$B:$B,MATCH("fully_loaded_cost_usd_per_fte_month",Assumptions!$A:$A,0))
A17: OpEx | B17: Legal | C17: =INDEX(Assumptions!$B:$B,MATCH("legal_retainer_usd_month",Assumptions!$A:$A,0))
A18: OpEx | B18: Accounting | C18: =INDEX(Assumptions!$B:$B,MATCH("accounting_bookkeeping_usd_month",Assumptions!$A:$A,0))
A19: OpEx | B19: Insurance | C19: =INDEX(Assumptions!$B:$B,MATCH("insurance_usd_month",Assumptions!$A:$A,0))
A20: OpEx | B20: Marketing and demand gen | C20: 0 | D20: Edit as you spend
A21: OpEx | B21: Travel and customer visits | C21: 0
A22: OpEx | B22: Software and tooling (non-COGS) | C22: 0
A24: EBITDA | B24: EBITDA (simplified) | C24: =C14-SUM(C16:C22)
A25: Cash | B25: Illustrative: cash impact vs EBITDA | C25: See runway model; link founder_draw and fundraising separately | D25: Not a full cash flow statement

Sheet Unit_Economics
A1: metric | B1: value_usd_or_count | C1: notes
A2: Jobs per tenant per month | B2: =INDEX(Assumptions!$B:$B,MATCH("jobs_per_tenant_per_day",Assumptions!$A:$A,0))*INDEX(Assumptions!$B:$B,MATCH("days_per_month",Assumptions!$A:$A,0))
A3: Token cost per job | B3: =(INDEX(Assumptions!$B:$B,MATCH("tokens_in_per_job",Assumptions!$A:$A,0))/1000000)*INDEX(Assumptions!$B:$B,MATCH("llm_price_in_per_million_tokens",Assumptions!$A:$A,0))+(INDEX(Assumptions!$B:$B,MATCH("tokens_out_per_job",Assumptions!$A:$A,0))/1000000)*INDEX(Assumptions!$B:$B,MATCH("llm_price_out_per_million_tokens",Assumptions!$A:$A,0))
A4: LLM COGS per tenant per month | B4: =C2*C3 | C4: jobs/month * cost/job
A5: Fleet LLM COGS per month | B5: =INDEX(Assumptions!$B:$B,MATCH("tenant_count",Assumptions!$A:$A,0))*C4
A6: Allocated compute per tenant (shared pool split) | B6: =(INDEX(Assumptions!$B:$B,MATCH("shared_vcpu_for_app_pool",Assumptions!$A:$A,0))*24*INDEX(Assumptions!$B:$B,MATCH("days_per_month",Assumptions!$A:$A,0))*INDEX(Assumptions!$B:$B,MATCH("vcpu_hour_usd",Assumptions!$A:$A,0)))/INDEX(Assumptions!$B:$B,MATCH("tenant_count",Assumptions!$A:$A,0))
A7: Storage + egress per tenant per month | B7: =INDEX(Assumptions!$B:$B,MATCH("storage_gb_per_tenant_month",Assumptions!$A:$A,0))*INDEX(Assumptions!$B:$B,MATCH("storage_usd_per_gb_month",Assumptions!$A:$A,0))+INDEX(Assumptions!$B:$B,MATCH("egress_gb_per_tenant_month",Assumptions!$A:$A,0))*INDEX(Assumptions!$B:$B,MATCH("egress_usd_per_gb",Assumptions!$A:$A,0))
A8: Variable COGS per tenant (LLM + storage + egress + allocated compute) | B8: =C4+C6+C7
A9: MRR per tenant | B9: =INDEX(Assumptions!$B:$B,MATCH("revenue_per_tenant_month",Assumptions!$A:$A,0))
A10: Contribution margin per tenant (MRR - variable COGS; excludes DB/overhead allocation) | B10: =C9-C8
A11: Simple LTV (revenue / monthly churn rate) — illustrative only | B11: =C9/((INDEX(Assumptions!$B:$B,MATCH("annual_churn_percent",Assumptions!$A:$A,0))/100)/12)
A12: CAC payback months (CAC / monthly contribution) | B12: =INDEX(Assumptions!$B:$B,MATCH("customer_acquisition_cost_usd",Assumptions!$A:$A,0))/C10

Sheet Pricing
A1: tier | B1: target_buyer | C1: price_anchor | D1: billing_model | E1: what_is_included | F1: hard_limits_or_caps | G1: notes
A2: Starter | B2: Individual or small team self-serve | C2: 49 | D2: per seat per month | E2: Core portal + N jobs included | F2: Concurrency seats GB retention | G2: Define overage for jobs and tokens
A3: Pro | B3: Team with SSO and audit needs | C3: 149 | D3: per seat per month | E3: SSO audit export longer retention | F3: Higher included credits | G3: Annual discount column in your real sheet
A4: Enterprise | B4: Regulated or large org | C4: custom | D4: annual contract + minimum | E4: BYOC or dedicated VPC SLA named support | F4: Negotiated limits | G4: Maps to Nexo sovereignty story
A5: Usage add-on | B5: Any | C5: 0.00 | D5: per 1k tokens or per job | E5: Pass-through or marked up | F5: Rate card | G5: Decide absorb vs BYOK

Sheet GTM_ICP
A1: topic | B1: field | C1: draft_content
A2: ICP | B2: Primary segment (pick one first) | C2: Security-conscious software teams needing auditable internal AI workflows on infrastructure they control
A3: ICP | B3: Secondary segment | C3: Managed service providers packaging Nexo for clients
A4: Positioning | B4: One-liner | C4: Private traceable AI workflows with enforced standards—not another generic chat wrapper
A5: Proof | B5: Design partner offer | C5: Paid pilot: scope success metrics deployment model support hours
A6: Channels | B6: Outbound | C6: LinkedIn email warm intros from users of air-gapped or compliance-heavy stacks
A7: Channels | B7: Inbound | C7: Technical content on audit trails BYOC deployment patterns
A8: Channels | B8: Community | C8: Open source users upgrading to support SLA
A9: Sales motion | B9: Low touch | C9: Self-serve Starter with Stripe and clear limits
A10: Sales motion | B10: High touch | C10: Enterprise security review architecture workshop
A11: Success criteria | B11: Pilot complete | C11: Time-to-first audited job run in customer environment under policy X

Sheet Readiness
A1: area | B1: item | C1: priority | D1: status_blank_todo_done | E1: owner_blank | F1: notes
A2: Legal | B2: Entity formation and cap table | C2: P0 | F2: Where you incorporate affects tax and contracts
A3: Legal | B3: MSA and order form templates | C3: P0 | F3: Limitation of liability indemnities SLA credits
A4: Legal | B4: DPA and subprocessors list if you host data | C4: P0 | F4: GDPR and state privacy laws
A5: Legal | B5: Terms of Service and Privacy Policy for SaaS site | C5: P0 | F5: Cookie consent if EU traffic
A6: Legal | B6: Export classification if applicable | C6: P2 | F6: Cryptography and dual-use when relevant
A7: Product | B7: Multi-tenant isolation model documented | C7: P0 | F7: Row-level vs schema vs cluster per tenant
A8: Product | B8: Authentication SSO SAML OIDC | C8: P1 | F8: Enterprise table stakes
A9: Product | B9: Billing metering and entitlements | C9: P0 | F9: Stripe Billing or equivalent usage aggregation
A10: Product | B10: Usage dashboards for customer | C10: P1 | F10: Transparency reduces disputes
A11: Security | B11: SOC2 roadmap or ISO27001 if enterprise | C11: P1 | F11: Many buyers require attestation or detailed SIG
A12: Security | B12: Incident response runbook | C12: P0 | F12: Who pages whom customer comms template
A13: Security | B13: Secrets management rotation | C13: P0 | F13: Per-tenant secrets if hosted
A14: Security | B14: Vulnerability disclosure policy | C14: P1
A15: Operations | B15: Backups restore tested | C15: P0 | F15: RPO RTO documented
A16: Operations | B16: Status page and comms templates | C16: P1
A17: Operations | B17: Support tiers and SLAs | C17: P0 | F17: Response times by severity
A18: Operations | B18: On-call rotation if 24x7 promised | C18: P1
A19: Finance | B19: Chart of accounts and revenue recognition | C19: P0 | F19: Annual vs monthly ASC606 basics with counsel
A20: Finance | B20: Sales tax VAT GST if applicable | C20: P1 | F20: Stripe Tax or Avalara
A21: Finance | B21: Runway model linked to hiring plan | C21: P0 | F21: Use Monthly_P_L tab
A22: People | B22: Founder employment agreement IP assignment | C22: P0 | F22: Clean chain of title to code
A23: People | B23: Offer letters and equity templates | C23: P1
A24: GTM | B24: Pricing page and packaging | C24: P0 | F24: See Pricing tab
A25: GTM | B25: Security FAQ and architecture one-pager | C25: P0 | F25: Shortens enterprise cycles
A26: GTM | B26: Reference customers and case studies | C26: P1 | F26: Even one strong logo helps

Sheet Risks
A1: risk | B1: impact | C1: likelihood | D1: mitigation | E1: owner_blank
A2: Heavy users erase margin on included LLM | B2: High | C2: Medium | D2: Meter jobs and tokens; BYOK tier; monthly minimums | E2: Product
A3: Security incident erodes trust | B3: High | C3: Low | D3: Least privilege logging encryption IR plan insurance | E3: Security
A4: Long enterprise sales cycles burn cash | B4: High | C4: Medium | D4: Paid pilots annual prepay services revenue | E4: GTM
A5: Vendor lock-in to single LLM provider price spikes | B5: Medium | C5: Medium | D5: Multi-provider abstraction pass-through pricing | E5: Engineering
A6: Scope creep on custom deployments | B6: Medium | C6: High | D6: Fixed SOWs change orders clear support boundaries | E6: CS
A7: Key person dependency | B7: High | C7: Medium | D7: Documentation runbooks hire or contractor bench | E7: Ops

Sheet KPIs
A1: kpi | B1: frequency | C1: target_blank | D1: actual_blank | E1: formula_or_data_source
A2: MRR | B2: Monthly | E2: Sum of subscription revenue
A3: Net new MRR | B3: Monthly | E3: New + expansion - contraction - churn
A4: Logo churn | B4: Monthly | E4: Customers lost / starting customers
A5: Revenue churn | B5: Monthly | E5: MRR lost from churned downsell / starting MRR
A6: Gross margin percent | B6: Monthly | E6: (Revenue - COGS) / Revenue define COGS consistently
A7: CAC | B7: Quarterly | E7: Sales+marketing spend / new customers in period
A8: LTV to CAC ratio | B8: Quarterly | E8: Cohort LTV / CAC
A9: Months payback | B9: Quarterly | E9: CAC / monthly gross margin per customer
A10: NPS or CSAT | B10: Quarterly | E10: Survey after key workflow
A11: P0 incidents | B11: Monthly | E11: Count from incident tracker
A12: Mean time to restore | B12: Monthly | E12: From incident data
A13: Gross burn | B13: Monthly | E13: Cash out excluding fundraising
A14: Runway months | B14: Monthly | E14: Cash / gross burn
